PyloXyloto/__init__.py
PyloXyloto/activations.py
PyloXyloto/data.py
PyloXyloto/layers.py
PyloXyloto/losses.py
PyloXyloto/metrics.py
PyloXyloto/model.py
PyloXyloto/net.py
PyloXyloto/utils.py
PyloXyloto/visualization.py
PyloXyloto-1.0.dist-info/LICENSE.txt
PyloXyloto-1.0.dist-info/METADATA
PyloXyloto-1.0.dist-info/WHEEL
PyloXyloto-1.0.dist-info/top_level.txt
PyloXyloto-1.0.dist-info/RECORD
